model_meter/__init__.py
model_meter/meter.py
model_meter-0.2.1.dist-info/LICENSE
model_meter-0.2.1.dist-info/METADATA
model_meter-0.2.1.dist-info/WHEEL
model_meter-0.2.1.dist-info/top_level.txt
model_meter-0.2.1.dist-info/RECORD
