Metadata-Version: 2.1
Name: model-meter
Version: 0.2.1
Summary: Model Meter
Home-page: https://github.com/dayeondev/ModelMeter
Author: Dayeon Oh
Author-email: dayeon.dev@gmail.com
License: MIT
Keywords: model meter
Classifier: Development Status :: 2 - Pre-Alpha
Classifier: Intended Audience :: Developers
Classifier: License :: OSI Approved :: MIT License
Classifier: Programming Language :: Python :: 3
Classifier: Operating System :: OS Independent
License-File: LICENSE
